wexample_filestate_javascript-0.0.14.dist-info/METADATA
wexample_filestate_javascript-0.0.14.dist-info/WHEEL
wexample_filestate_javascript-0.0.14.dist-info/entry_points.txt
wexample_filestate_javascript/__init__.py
wexample_filestate_javascript/config_option/__init__.py
wexample_filestate_javascript/config_option/biome_config_option.py
wexample_filestate_javascript/config_value/__init__.py
wexample_filestate_javascript/config_value/javascript_config_value.py
wexample_filestate_javascript/const/__init__.py
wexample_filestate_javascript/const/javascript_file.py
wexample_filestate_javascript/file/__init__.py
wexample_filestate_javascript/file/javascript_file.py
wexample_filestate_javascript/option/__init__.py
wexample_filestate_javascript/option/javascript/__init__.py
wexample_filestate_javascript/option/javascript/abstract_javascript_file_content_option.py
wexample_filestate_javascript/option/javascript/biome_option.py
wexample_filestate_javascript/option/javascript_option.py
wexample_filestate_javascript/options_provider/__init__.py
wexample_filestate_javascript/options_provider/javascript_options_provider.py
wexample_filestate_javascript/py.typed
wexample_filestate_javascript/resources/__init__.py
wexample_filestate_javascript/resources/docker/Dockerfile.javascript-option
wexample_filestate_javascript/resources/docker/__init__.py
wexample_filestate_javascript/resources/docker/biome.json
wexample_filestate_javascript-0.0.14.dist-info/RECORD
